tenetsec/__init__.py
tenetsec/ai_recommendations.py
tenetsec/auth.py
tenetsec/graph_client.py
tenetsec/main.py
tenetsec/report.py
tenetsec/assessments/__init__.py
tenetsec/assessments/base.py
tenetsec/assessments/defender.py
tenetsec/assessments/exchange.py
tenetsec/assessments/identity.py
tenetsec/assessments/sharepoint.py
tenetsec/assessments/teams.py
tenetsec-0.1.0.dist-info/LICENSE
tenetsec-0.1.0.dist-info/METADATA
tenetsec-0.1.0.dist-info/WHEEL
tenetsec-0.1.0.dist-info/entry_points.txt
tenetsec-0.1.0.dist-info/top_level.txt
tenetsec-0.1.0.dist-info/RECORD
