Metadata-Version: 2.2
Name: tenetsec
Version: 0.1.0
Summary: Microsoft 365 Security Assessment Tool
Author: TenetSec
Author-email: info@tenetsec.example.com
Requires-Python: >=3.8
License-File: LICENSE
Requires-Dist: msal>=1.20.0
Requires-Dist: requests>=2.28.1
Requires-Dist: pandas>=1.5.0
Requires-Dist: matplotlib>=3.6.0
Requires-Dist: seaborn>=0.12.0
Requires-Dist: python-dotenv>=0.21.0
Requires-Dist: rich>=12.6.0
Requires-Dist: PyYAML>=6.0
Dynamic: author
Dynamic: author-email
Dynamic: requires-dist
Dynamic: requires-python
Dynamic: summary
